pyrelist/__init__.py
pyrelist/configs.py
pyrelist/main.py
pyrelist/python.py
pyrelist/static.py
pyrelist/utils.py
pyrelist-0.0.5.dist-info/LICENSE
pyrelist-0.0.5.dist-info/METADATA
pyrelist-0.0.5.dist-info/WHEEL
pyrelist-0.0.5.dist-info/entry_points.txt
pyrelist-0.0.5.dist-info/top_level.txt
pyrelist-0.0.5.dist-info/RECORD
