Metadata-Version: 2.1
Name: pyrelist
Version: 0.0.5
Summary: Pyrelist helps you match a file against multiple regex patterns
Home-page: https://veltzer.github.io/pyrelist
Download-URL: https://github.com/veltzer/pyrelist
Author: Mark Veltzer
Author-email: mark.veltzer@gmail.com
Maintainer: Mark Veltzer
Maintainer-email: mark.veltzer@gmail.com
License: MIT
Keywords: regexp,lint
Platform: python3
Classifier: Development Status :: 4 - Beta
Classifier: Environment :: Console
Classifier: Operating System :: OS Independent
Classifier: Programming Language :: Python
Classifier: Programming Language :: Python :: 3
Classifier: Programming Language :: Python :: 3 :: Only
Classifier: Programming Language :: Python :: 3.11
Classifier: Topic :: Utilities
Classifier: License :: OSI Approved :: MIT License
License-File: LICENSE
Requires-Dist: pylogconf
Requires-Dist: pytconf
